MANIFEST.in
README.md
setup.py
bin/hanglish
bin/words.dict
hanglish/__init__.py
hanglish.egg-info/PKG-INFO
hanglish.egg-info/SOURCES.txt
hanglish.egg-info/dependency_links.txt
hanglish.egg-info/top_level.txt