Metadata-Version: 1.0
Name: hanglish
Version: 1.0.1
Summary: It is a simple tool for finding text you want to search from the folder you want.
Home-page: https://github.com/pmars/hanglish
Author: xiaoh
Author-email: xiaoh@about.me
License: MIT Licence
Keywords: hanglish,hangman,game,xingming,xiaoh,english,learning
Platform: UNKNOWN
